explicit/dlq/__init__.py
explicit/dlq/config.py
explicit/dlq/py.typed
explicit/dlq/types.py
explicit/dlq/adapters/__init__.py
explicit/dlq/adapters/db.py
explicit/dlq/contrib/__init__.py
explicit/dlq/contrib/django/README.md
explicit/dlq/contrib/django/__init__.py
explicit/dlq/contrib/django/apps.py
explicit/dlq/contrib/django/models.py
explicit/dlq/contrib/django/adapters/__init__.py
explicit/dlq/contrib/django/adapters/db.py
explicit/dlq/contrib/django/migrations/0001_initial.py
explicit/dlq/contrib/django/migrations/__init__.py
explicit/dlq/contrib/drf/README.md
explicit/dlq/contrib/drf/__init__.py
explicit/dlq/contrib/drf/serializers.py
explicit/dlq/contrib/drf/views.py
explicit/dlq/domain/__init__.py
explicit/dlq/domain/commands.py
explicit/dlq/domain/factories.py
explicit/dlq/domain/model.py
explicit/dlq/domain/services.py
explicit/dlq/infrastructure/__init__.py
explicit/dlq/infrastructure/handlers.py
explicit/dlq/services/__init__.py
explicit/dlq/services/handlers.py
explicit_python_dlq-1.0.0.dist-info/METADATA
explicit_python_dlq-1.0.0.dist-info/WHEEL
explicit_python_dlq-1.0.0.dist-info/top_level.txt
explicit_python_dlq-1.0.0.dist-info/RECORD
