Metadata-Version: 2.4
Name: explicit-python-dlq
Version: 1.0.0
Summary: Набор компонентов реализующих DQL для систем на базе explicit
Author-email: "АО \"БАРС Груп\"" <education_dev@bars-open.ru>
Classifier: Intended Audience :: Developers
Classifier: Environment :: Web Environment
Classifier: Natural Language :: Russian
Classifier: Operating System :: OS Independent
Classifier: Development Status :: 5 - Production/Stable
Classifier: Programming Language :: Python :: 3.9
Classifier: Programming Language :: Python :: 3.10
Classifier: Programming Language :: Python :: 3.11
Classifier: Programming Language :: Python :: 3.12
Requires-Python: >=3.9
Requires-Dist: explicit-python<3,>=2.2.1
Provides-Extra: dev
Requires-Dist: freezegun; extra == "dev"
Provides-Extra: django
Requires-Dist: explicit-python-django<2.0,>=1.0.2; extra == "django"
Provides-Extra: rest
Requires-Dist: djangorestframework>=3.13.0; extra == "rest"
Requires-Dist: django_filter>=23.3; extra == "rest"
